arth_temperature/__init__.py
arth_temperature/temperature.py
arth_temperature-1.0.0.dist-info/METADATA
arth_temperature-1.0.0.dist-info/WHEEL
arth_temperature-1.0.0.dist-info/licenses/LICENCE.txt
arth_temperature-1.0.0.dist-info/RECORD
