Metadata-Version: 2.1
Name: arth_temperature
Version: 1.0.0
Summary: A package to convert temperature from one scale to another
Author-email: Arth Jaiswal <jaiswalarth17052004@gmail.com>
License-File: LICENCE.txt
Classifier: License :: OSI Approved :: MIT License
Classifier: Operating System :: OS Independent
Classifier: Programming Language :: Python :: 3
Requires-Python: >=3.7
